[
  {
    "id": "cf1860e058c26a7f9",
    "createdAt": "2026-02-07T20:58:23.433Z",
    "updatedAt": "2026-04-08T20:58:24.446Z",
    "userId": "usr_4e75418feda8",
    "accountId": "cb4ec8a09f93325fd",
    "amount": 15159,
    "type": "CREDIT",
    "description": "Initial Payroll Setup",
    "status": "COMPLETED",
    "reference": "REFA6A96652"
  },
  {
    "id": "c8ea823d2da043862",
    "createdAt": "2026-02-22T08:42:53.559Z",
    "updatedAt": "2026-04-08T20:58:24.448Z",
    "userId": "usr_4e75418feda8",
    "accountId": "cb4ec8a09f93325fd",
    "amount": 542,
    "type": "DEBIT",
    "description": "Supermarket",
    "status": "COMPLETED",
    "reference": "REF8A2C33F8"
  },
  {
    "id": "ce01d4643fc933a6a",
    "createdAt": "2026-03-01T20:58:54.021Z",
    "updatedAt": "2026-04-08T20:58:24.449Z",
    "userId": "usr_4e75418feda8",
    "accountId": "cb4ec8a09f93325fd",
    "amount": 508,
    "type": "DEBIT",
    "description": "Supermarket",
    "status": "COMPLETED",
    "reference": "REF5DAB6ED4"
  },
  {
    "id": "c496b98342e1e9776",
    "createdAt": "2026-02-21T20:32:55.835Z",
    "updatedAt": "2026-04-08T20:58:24.451Z",
    "userId": "usr_4e75418feda8",
    "accountId": "cb4ec8a09f93325fd",
    "amount": 257,
    "type": "DEBIT",
    "description": "Supermarket",
    "status": "COMPLETED",
    "reference": "REF68EB6236"
  },
  {
    "id": "cde574d8354b01452",
    "createdAt": "2026-02-09T13:55:56.767Z",
    "updatedAt": "2026-04-08T20:58:24.452Z",
    "userId": "usr_4e75418feda8",
    "accountId": "cb4ec8a09f93325fd",
    "amount": 1240,
    "type": "CREDIT",
    "description": "Dividend Payout",
    "status": "COMPLETED",
    "reference": "REFD6AB9EAF"
  },
  {
    "id": "cdc236a56845648a7",
    "createdAt": "2026-03-22T13:38:53.164Z",
    "updatedAt": "2026-04-08T20:58:24.454Z",
    "userId": "usr_4e75418feda8",
    "accountId": "cb4ec8a09f93325fd",
    "amount": 625,
    "type": "DEBIT",
    "description": "Utility Electric",
    "status": "COMPLETED",
    "reference": "REF5DE358EA"
  },
  {
    "id": "c48d6fa1ada508e9d",
    "createdAt": "2026-03-04T20:24:04.228Z",
    "updatedAt": "2026-04-08T20:58:24.455Z",
    "userId": "usr_4e75418feda8",
    "accountId": "cb4ec8a09f93325fd",
    "amount": 638,
    "type": "DEBIT",
    "description": "Supermarket",
    "status": "COMPLETED",
    "reference": "REF7D5D26F0"
  },
  {
    "id": "cd65278b72c219180",
    "createdAt": "2026-02-24T00:32:41.649Z",
    "updatedAt": "2026-04-08T20:58:24.456Z",
    "userId": "usr_4e75418feda8",
    "accountId": "cb4ec8a09f93325fd",
    "amount": 1536,
    "type": "CREDIT",
    "description": "Dividend Payout",
    "status": "COMPLETED",
    "reference": "REF79C811F3"
  },
  {
    "id": "c924e853a8ea1438d",
    "createdAt": "2026-03-02T19:59:36.362Z",
    "updatedAt": "2026-04-08T20:58:24.458Z",
    "userId": "usr_4e75418feda8",
    "accountId": "cb4ec8a09f93325fd",
    "amount": 684,
    "type": "DEBIT",
    "description": "POS Purchase Apple",
    "status": "COMPLETED",
    "reference": "REF9F54EB7E"
  },
  {
    "id": "cb272c697b99d7dbc",
    "createdAt": "2026-02-23T00:24:03.777Z",
    "updatedAt": "2026-04-08T20:58:24.460Z",
    "userId": "usr_4e75418feda8",
    "accountId": "cb4ec8a09f93325fd",
    "amount": 496,
    "type": "DEBIT",
    "description": "POS Purchase Apple",
    "status": "COMPLETED",
    "reference": "REFE1F7DDEA"
  },
  {
    "id": "c9b397b0cd57e21e3",
    "createdAt": "2026-04-04T08:27:14.659Z",
    "updatedAt": "2026-04-08T20:58:24.462Z",
    "userId": "usr_4e75418feda8",
    "accountId": "cb4ec8a09f93325fd",
    "amount": 331,
    "type": "DEBIT",
    "description": "Amazon Shopping",
    "status": "COMPLETED",
    "reference": "REFF4A8362F"
  },
  {
    "id": "cb6ac01f9a805faac",
    "createdAt": "2026-04-08T20:23:08.922Z",
    "updatedAt": "2026-04-08T20:58:24.464Z",
    "userId": "usr_4e75418feda8",
    "accountId": "cb4ec8a09f93325fd",
    "amount": 411,
    "type": "DEBIT",
    "description": "POS Purchase Apple",
    "status": "COMPLETED",
    "reference": "REF510F14EE"
  },
  {
    "id": "c06cda1562f33d32a",
    "createdAt": "2026-03-08T10:16:36.606Z",
    "updatedAt": "2026-04-08T20:58:24.465Z",
    "userId": "usr_4e75418feda8",
    "accountId": "cb4ec8a09f93325fd",
    "amount": 1939,
    "type": "CREDIT",
    "description": "Dividend Payout",
    "status": "COMPLETED",
    "reference": "REF1C5D2A58"
  },
  {
    "id": "c92df644322575764",
    "createdAt": "2026-02-23T03:05:43.805Z",
    "updatedAt": "2026-04-08T20:58:24.467Z",
    "userId": "usr_4e75418feda8",
    "accountId": "cb4ec8a09f93325fd",
    "amount": 557,
    "type": "DEBIT",
    "description": "Amazon Shopping",
    "status": "COMPLETED",
    "reference": "REFEEDD617C"
  },
  {
    "id": "cfe9901ef17ac923f",
    "createdAt": "2026-03-24T06:51:35.471Z",
    "updatedAt": "2026-04-08T20:58:24.468Z",
    "userId": "usr_4e75418feda8",
    "accountId": "cb4ec8a09f93325fd",
    "amount": 929,
    "type": "CREDIT",
    "description": "External Transfer Credit",
    "status": "COMPLETED",
    "reference": "REF7F39EB74"
  },
  {
    "id": "c1d107b3a8877c70e",
    "createdAt": "2026-03-26T21:13:23.584Z",
    "updatedAt": "2026-04-08T20:58:24.470Z",
    "userId": "usr_4e75418feda8",
    "accountId": "cb4ec8a09f93325fd",
    "amount": 142,
    "type": "DEBIT",
    "description": "POS Purchase Apple",
    "status": "COMPLETED",
    "reference": "REF68C0E580"
  },
  {
    "id": "cbad6ca7ede5769a6",
    "createdAt": "2026-03-14T01:59:33.644Z",
    "updatedAt": "2026-04-08T20:58:24.472Z",
    "userId": "usr_4e75418feda8",
    "accountId": "cb4ec8a09f93325fd",
    "amount": 2513,
    "type": "CREDIT",
    "description": "External Transfer Credit",
    "status": "COMPLETED",
    "reference": "REF987BB624"
  },
  {
    "id": "c67ef24b2a8f9336a",
    "createdAt": "2026-03-09T02:28:50.840Z",
    "updatedAt": "2026-04-08T20:58:24.473Z",
    "userId": "usr_4e75418feda8",
    "accountId": "cb4ec8a09f93325fd",
    "amount": 2721,
    "type": "CREDIT",
    "description": "External Transfer Credit",
    "status": "COMPLETED",
    "reference": "REF1D9B178D"
  },
  {
    "id": "c6a2d140eca1ccb59",
    "createdAt": "2026-02-27T09:26:01.326Z",
    "updatedAt": "2026-04-08T20:58:24.475Z",
    "userId": "usr_4e75418feda8",
    "accountId": "cb4ec8a09f93325fd",
    "amount": 29,
    "type": "DEBIT",
    "description": "POS Purchase Apple",
    "status": "COMPLETED",
    "reference": "REF07655561"
  },
  {
    "id": "cbc8a9231a44d2bca",
    "createdAt": "2026-02-22T22:46:27.112Z",
    "updatedAt": "2026-04-08T20:58:24.477Z",
    "userId": "usr_4e75418feda8",
    "accountId": "cb4ec8a09f93325fd",
    "amount": 361,
    "type": "DEBIT",
    "description": "Supermarket",
    "status": "COMPLETED",
    "reference": "REFF1AC0682"
  },
  {
    "id": "c04529d196c06d262",
    "createdAt": "2026-04-02T01:21:28.357Z",
    "updatedAt": "2026-04-08T20:58:24.478Z",
    "userId": "usr_4e75418feda8",
    "accountId": "cb4ec8a09f93325fd",
    "amount": 118,
    "type": "DEBIT",
    "description": "POS Purchase Apple",
    "status": "COMPLETED",
    "reference": "REFEC0A627A"
  },
  {
    "id": "ced0dc1061d3a4b48",
    "createdAt": "2026-02-20T03:46:06.680Z",
    "updatedAt": "2026-04-08T20:58:24.480Z",
    "userId": "usr_4e75418feda8",
    "accountId": "cb4ec8a09f93325fd",
    "amount": 1711,
    "type": "CREDIT",
    "description": "Salary Deposit",
    "status": "COMPLETED",
    "reference": "REF6ADC344B"
  },
  {
    "id": "c63dec6a1c347d805",
    "createdAt": "2026-03-20T06:13:08.234Z",
    "updatedAt": "2026-04-08T20:58:24.482Z",
    "userId": "usr_4e75418feda8",
    "accountId": "cb4ec8a09f93325fd",
    "amount": 2448,
    "type": "CREDIT",
    "description": "External Transfer Credit",
    "status": "COMPLETED",
    "reference": "REF11FF4A00"
  },
  {
    "id": "c159809291385c06d",
    "createdAt": "2026-03-14T08:24:37.432Z",
    "updatedAt": "2026-04-08T20:58:24.483Z",
    "userId": "usr_4e75418feda8",
    "accountId": "cb4ec8a09f93325fd",
    "amount": 265,
    "type": "DEBIT",
    "description": "Amazon Shopping",
    "status": "COMPLETED",
    "reference": "REFC41A81FB"
  },
  {
    "id": "c3bbc0ecbba799753",
    "createdAt": "2026-02-11T03:19:02.693Z",
    "updatedAt": "2026-04-08T20:58:24.485Z",
    "userId": "usr_4e75418feda8",
    "accountId": "cb4ec8a09f93325fd",
    "amount": 356,
    "type": "DEBIT",
    "description": "POS Purchase Apple",
    "status": "COMPLETED",
    "reference": "REF6B402F36"
  },
  {
    "id": "ca448288d4fa04b0e",
    "createdAt": "2026-03-12T03:51:16.356Z",
    "updatedAt": "2026-04-08T20:58:24.487Z",
    "userId": "usr_4e75418feda8",
    "accountId": "cb4ec8a09f93325fd",
    "amount": 157,
    "type": "DEBIT",
    "description": "Supermarket",
    "status": "COMPLETED",
    "reference": "REF9056703C"
  },
  {
    "id": "c20322ecdbaa1343e",
    "createdAt": "2026-02-13T00:48:50.254Z",
    "updatedAt": "2026-04-08T20:58:24.488Z",
    "userId": "usr_4e75418feda8",
    "accountId": "cb4ec8a09f93325fd",
    "amount": 454,
    "type": "DEBIT",
    "description": "Utility Electric",
    "status": "COMPLETED",
    "reference": "REF4ADF3C89"
  },
  {
    "id": "c8ed1e1dbfc2e3b2f",
    "createdAt": "2026-02-26T02:48:30.046Z",
    "updatedAt": "2026-04-08T20:58:24.490Z",
    "userId": "usr_4e75418feda8",
    "accountId": "cb4ec8a09f93325fd",
    "amount": 2045,
    "type": "CREDIT",
    "description": "External Transfer Credit",
    "status": "COMPLETED",
    "reference": "REF571CC13C"
  },
  {
    "id": "c841c98315f1e42dc",
    "createdAt": "2026-02-13T11:17:36.111Z",
    "updatedAt": "2026-04-08T20:58:24.491Z",
    "userId": "usr_4e75418feda8",
    "accountId": "cb4ec8a09f93325fd",
    "amount": 531,
    "type": "DEBIT",
    "description": "Utility Electric",
    "status": "COMPLETED",
    "reference": "REF56676E82"
  },
  {
    "id": "c4c7813b6c27dba39",
    "createdAt": "2026-02-17T03:10:15.642Z",
    "updatedAt": "2026-04-08T20:58:24.494Z",
    "userId": "usr_4e75418feda8",
    "accountId": "cb4ec8a09f93325fd",
    "amount": 496,
    "type": "DEBIT",
    "description": "Supermarket",
    "status": "COMPLETED",
    "reference": "REF96A9E85F"
  },
  {
    "id": "c9e8ce5ed351f562a",
    "createdAt": "2026-02-27T10:07:43.910Z",
    "updatedAt": "2026-04-08T20:58:24.495Z",
    "userId": "usr_4e75418feda8",
    "accountId": "cb4ec8a09f93325fd",
    "amount": 236,
    "type": "DEBIT",
    "description": "Amazon Shopping",
    "status": "COMPLETED",
    "reference": "REFD1DF13A0"
  },
  {
    "id": "c12ed9eb67abf3d87",
    "createdAt": "2026-03-28T02:42:08.881Z",
    "updatedAt": "2026-04-08T20:58:24.497Z",
    "userId": "usr_4e75418feda8",
    "accountId": "cb4ec8a09f93325fd",
    "amount": 323,
    "type": "DEBIT",
    "description": "Utility Electric",
    "status": "COMPLETED",
    "reference": "REFBB702D32"
  },
  {
    "id": "c4df08377005ad206",
    "createdAt": "2026-03-09T11:33:55.051Z",
    "updatedAt": "2026-04-08T20:58:24.499Z",
    "userId": "usr_4e75418feda8",
    "accountId": "cb4ec8a09f93325fd",
    "amount": 174,
    "type": "DEBIT",
    "description": "Amazon Shopping",
    "status": "COMPLETED",
    "reference": "REF0FF767C4"
  },
  {
    "id": "cf2eabbd64b6cf776",
    "createdAt": "2026-02-27T19:45:37.649Z",
    "updatedAt": "2026-04-08T20:58:24.500Z",
    "userId": "usr_4e75418feda8",
    "accountId": "cb4ec8a09f93325fd",
    "amount": 248,
    "type": "DEBIT",
    "description": "POS Purchase Apple",
    "status": "COMPLETED",
    "reference": "REFB640CA87"
  },
  {
    "id": "cff1255309e80de9b",
    "createdAt": "2026-04-07T01:39:43.137Z",
    "updatedAt": "2026-04-08T20:58:24.502Z",
    "userId": "usr_4e75418feda8",
    "accountId": "cb4ec8a09f93325fd",
    "amount": 272,
    "type": "DEBIT",
    "description": "Supermarket",
    "status": "COMPLETED",
    "reference": "REF0B42BA73"
  },
  {
    "id": "ce1ce0c9b1ec4ae6b",
    "createdAt": "2026-04-02T15:53:35.214Z",
    "updatedAt": "2026-04-08T20:58:24.503Z",
    "userId": "usr_4e75418feda8",
    "accountId": "cb4ec8a09f93325fd",
    "amount": 144,
    "type": "DEBIT",
    "description": "Utility Electric",
    "status": "COMPLETED",
    "reference": "REF01B31092"
  },
  {
    "id": "cd69aeb6f4e1198ce",
    "createdAt": "2026-02-25T01:30:46.316Z",
    "updatedAt": "2026-04-08T20:58:24.505Z",
    "userId": "usr_4e75418feda8",
    "accountId": "cb4ec8a09f93325fd",
    "amount": 724,
    "type": "DEBIT",
    "description": "Utility Electric",
    "status": "COMPLETED",
    "reference": "REF888696C9"
  },
  {
    "id": "c05d05f4b6910c7b0",
    "createdAt": "2026-04-02T17:15:43.142Z",
    "updatedAt": "2026-04-08T20:58:24.506Z",
    "userId": "usr_4e75418feda8",
    "accountId": "cb4ec8a09f93325fd",
    "amount": 508,
    "type": "DEBIT",
    "description": "Supermarket",
    "status": "COMPLETED",
    "reference": "REF04876BCA"
  },
  {
    "id": "c5bfc291c472d190e",
    "createdAt": "2026-03-26T20:12:58.469Z",
    "updatedAt": "2026-04-08T20:58:24.508Z",
    "userId": "usr_4e75418feda8",
    "accountId": "cb4ec8a09f93325fd",
    "amount": 2542,
    "type": "CREDIT",
    "description": "Dividend Payout",
    "status": "COMPLETED",
    "reference": "REF96FD0C18"
  },
  {
    "id": "c00266e3b3223ef04",
    "createdAt": "2026-04-07T13:19:05.599Z",
    "updatedAt": "2026-04-08T20:58:24.509Z",
    "userId": "usr_4e75418feda8",
    "accountId": "cb4ec8a09f93325fd",
    "amount": 635,
    "type": "DEBIT",
    "description": "Supermarket",
    "status": "COMPLETED",
    "reference": "REF309BCE51"
  },
  {
    "id": "c0661803340ff25fe",
    "createdAt": "2026-03-22T04:41:51.906Z",
    "updatedAt": "2026-04-08T20:58:24.511Z",
    "userId": "usr_4e75418feda8",
    "accountId": "cb4ec8a09f93325fd",
    "amount": 287,
    "type": "DEBIT",
    "description": "Utility Electric",
    "status": "COMPLETED",
    "reference": "REFA41EC1B3"
  }
]